{
  "schema_version": 1,
  "plugin_min_version": "0.1.0",
  "id": "fx-space-01",
  "display_name": "FX Space 01",
  "author": "Factory",
  "description": "Lab-authored FX-forward pluck that stresses delay, reverb, phaser, EQ, compressor, and saturation wet proof.",
  "tags": ["fx", "space", "pluck", "wet"],
  "parameters": {
    "voice.mode": "Poly",
    "voice.polyphony": 6,
    "voice.unison_count": 2,
    "osc.saw_level": 0.56,
    "osc.pulse_level": 0.24,
    "osc.noise_level": 0.03,
    "osc.stack_count": 2,
    "osc.stack_detune": 0.1,
    "osc.pulse_width": 0.38,
    "filter.mode": "B2",
    "filter.cutoff_semitones": 70.0,
    "filter.resonance": 0.34,
    "filter.drive": 0.28,
    "direct.filter_lfo_semitones": 12.0,
    "direct.filter_mod_env_semitones": 18.0,
    "amp_env.attack_ms": 3.0,
    "amp_env.decay_ms": 300.0,
    "amp_env.sustain": 0.1,
    "amp_env.release_ms": 260.0,
    "mod_env.attack_ms": 1.0,
    "mod_env.decay_ms": 440.0,
    "mod_env.sustain": 0.0,
    "mod_env.release_ms": 160.0,
    "lfo.shape": "Triangle",
    "lfo.rate_mode": "Sync",
    "lfo.sync_division": "1/4",
    "lfo.gate_mode": "PolyOn",
    "lfo.mono": false,
    "ramp.enabled": true,
    "ramp.mode": "OneShot",
    "ramp.rise_ms": 220.0,
    "ramp.curve": "Snappy",
    "layer.1.enabled": true,
    "layer.1.osc.1.enabled": true,
    "layer.1.osc.1.voices": 2,
    "layer.1.osc.1.waveform": "Pulse",
    "layer.1.osc.1.level": 0.58,
    "layer.1.osc.1.detune": 0.09,
    "layer.1.osc.1.stereo": 0.55,
    "layer.1.osc.2.enabled": true,
    "layer.1.osc.2.voices": 1,
    "layer.1.osc.2.waveform": "Saw",
    "layer.1.osc.2.note": 12,
    "layer.1.osc.2.level": 0.18,
    "layer.2.enabled": true,
    "layer.2.level_db": -8.0,
    "layer.2.osc.1.enabled": true,
    "layer.2.osc.1.voices": 1,
    "layer.2.osc.1.waveform": "Noise",
    "layer.2.osc.1.level": 0.04,
    "transmod.1.enabled": true,
    "transmod.1.source": "Ramp",
    "transmod.1.scaler": "Macro1",
    "transmod.1.filter_cutoff_semitones": 10.0,
    "transmod.2.enabled": true,
    "transmod.2.source": "RandomOnNote",
    "transmod.2.scaler": "Macro2",
    "transmod.2.pan": 0.18,
    "amp.drive": 0.16,
    "amp.level_db": -14.0,
    "amp.pan_spread": 0.52,
    "amp.unison_spread": 0.36,
    "amp.analog": 0.06,
    "fx.enabled": true,
    "fx.saturation_enabled": true,
    "fx.distortion_mode": "Fold",
    "fx.saturation_mix": 0.12,
    "fx.saturation_drive": 0.44,
    "fx.phaser_enabled": true,
    "fx.phaser_mix": 0.22,
    "fx.phaser_rate_hz": 0.32,
    "fx.phaser_depth": 0.62,
    "fx.phaser_feedback": 0.28,
    "fx.chorus_enabled": true,
    "fx.chorus_mix": 0.14,
    "fx.chorus_rate_hz": 0.4,
    "fx.chorus_depth_ms": 6.0,
    "fx.eq_enabled": true,
    "fx.eq_low_gain_db": -1.0,
    "fx.eq_high_gain_db": 2.5,
    "fx.delay_enabled": true,
    "fx.delay_mix": 0.32,
    "fx.delay_sync_division": "1/8D",
    "fx.delay_feedback": 0.44,
    "fx.reverb_enabled": true,
    "fx.reverb_mix": 0.34,
    "fx.reverb_decay": 0.78,
    "fx.compressor_enabled": true,
    "fx.compressor_threshold_db": -22.0,
    "fx.compressor_ratio": 2.5,
    "fx.compressor_makeup_db": 0.5,
    "fx.compressor_mix": 0.5,
    "quality.realtime_mode": "Normal",
    "quality.offline_mode": "High",
    "macro.motion": 0.64,
    "macro.width": 0.6,
    "macro.drive": 0.4,
    "macro.space": 0.62
  },
  "mod_slots": [
    {
      "slot_id": 1,
      "enabled": true,
      "source": "Ramp",
      "scaler": "Macro1",
      "depths": {
        "filter.cutoff_semitones": 10.0
      },
      "depth_domain": "Physical"
    },
    {
      "slot_id": 2,
      "enabled": true,
      "source": "RandomOnNote",
      "scaler": "Macro2",
      "depths": {
        "amp.pan": 0.18
      },
      "depth_domain": "Normalized"
    }
  ],
  "macros": [
    {
      "id": "motion",
      "display_name": "Motion",
      "value": 0.64,
      "assignments": []
    },
    {
      "id": "width",
      "display_name": "Width",
      "value": 0.6,
      "assignments": []
    },
    {
      "id": "drive",
      "display_name": "Drive",
      "value": 0.4,
      "assignments": []
    },
    {
      "id": "space",
      "display_name": "Space",
      "value": 0.62,
      "assignments": []
    }
  ],
  "metadata": {
    "program": "synthia_lab_rebuild",
    "browser": {
      "bank": "Factory",
      "category": "FX",
      "source": "factory"
    },
    "implementation_note": "Lab-authored Phase 1 patch recreation preset; not a third-party preset clone."
  }
}
